pydor.py
pydor-0.0.dist-info/LICENSE
pydor-0.0.dist-info/METADATA
pydor-0.0.dist-info/WHEEL
pydor-0.0.dist-info/entry_points.txt
pydor-0.0.dist-info/top_level.txt
pydor-0.0.dist-info/zip-safe
pydor-0.0.dist-info/RECORD
